ezcache/__init__.py
ezcache/_types.py
ezcache/_utils.py
ezcache/api.py
ezcache-0.1.3.dist-info/METADATA
ezcache-0.1.3.dist-info/WHEEL
ezcache-0.1.3.dist-info/licenses/LICENSE
ezcache-0.1.3.dist-info/RECORD
